diswarm_handler/__init__.py
diswarm_handler-1.1.dist-info/LICENSE
diswarm_handler-1.1.dist-info/METADATA
diswarm_handler-1.1.dist-info/WHEEL
diswarm_handler-1.1.dist-info/top_level.txt
diswarm_handler-1.1.dist-info/RECORD
