Metadata-Version: 2.1
Name: diswarm-handler
Version: 1.1
Summary: Handler for DiSwarm
Home-page: https://github.com/iTecAI/DiSwarm/tree/master/diswarm-handler
Author: iTecX
Author-email: matteovh@gmail.com
License: UNKNOWN
Platform: UNKNOWN
Classifier: Programming Language :: Python :: 3
Classifier: License :: OSI Approved :: MIT License
Classifier: Operating System :: OS Independent
Requires-Dist: DiSwarm
